qmpy/VERSION.txt
qmpy/__init__.py
qmpy/models.py
qmpy/tests.py
qmpy/analysis/__init__.py
qmpy/analysis/bond_valence.py
qmpy/analysis/database.py
qmpy/analysis/elastic.py
qmpy/analysis/griddata.py
qmpy/analysis/interface_finder.py
qmpy/analysis/miedema.py
qmpy/analysis/mining.py
qmpy/analysis/nearest_neighbors.py
qmpy/analysis/network.py
qmpy/analysis/nn.pyx
qmpy/analysis/pdf.py
qmpy/analysis/tests.py
qmpy/analysis/xrd.py
qmpy/analysis/debye/debye_model.py
qmpy/analysis/debye/quasi_harmonic.py
qmpy/analysis/debye/read_file.py
qmpy/analysis/debye/sound_waves.py
qmpy/analysis/debye/exp_PbS/PbS_answers
qmpy/analysis/debye/exp_PbS/PbS_debye
qmpy/analysis/debye/exp_PbS/PbS_density
qmpy/analysis/debye/exp_PbS/PbS_exp_C
qmpy/analysis/debye/exp_PbTe/PbTe_density
qmpy/analysis/debye/exp_PbTe/PbTe_exp_C
qmpy/analysis/debye/exp_PbTe/PbTe_model_VII_C
qmpy/analysis/debye/lead/Pb_answers
qmpy/analysis/debye/lead/Pb_debey_temp
qmpy/analysis/debye/lead/Pb_density
qmpy/analysis/debye/lead/Pb_exp_C
qmpy/analysis/debye/wolfram_tungsten/W_density
qmpy/analysis/debye/wolfram_tungsten/W_exp_C
qmpy/analysis/symmetry/__init__.py
qmpy/analysis/symmetry/routines.py
qmpy/analysis/symmetry/spacegroup.py
qmpy/analysis/symmetry/tests.py
qmpy/analysis/test/bond_valence_test.py
qmpy/analysis/test/dists.txt
qmpy/analysis/test/ising_test.py
qmpy/analysis/test/nn_test.py
qmpy/analysis/test/pdf_test.py
qmpy/analysis/test/peaks.txt
qmpy/analysis/test/xrd_test.py
qmpy/analysis/thermodynamics/__init__.py
qmpy/analysis/thermodynamics/chemical_potential_fitting.py
qmpy/analysis/thermodynamics/convex_hull.py
qmpy/analysis/thermodynamics/equilibrium.py
qmpy/analysis/thermodynamics/phase.py
qmpy/analysis/thermodynamics/reaction.py
qmpy/analysis/thermodynamics/setup.py
qmpy/analysis/thermodynamics/space.py
qmpy/analysis/thermodynamics/tests.py
qmpy/analysis/vasp/__init__.py
qmpy/analysis/vasp/calculation.py
qmpy/analysis/vasp/dos.py
qmpy/analysis/vasp/potential.py
qmpy/analysis/vasp/files/convergence/CHG
qmpy-1.4.0.dist-info/LICENSE.txt
qmpy-1.4.0.dist-info/METADATA
qmpy-1.4.0.dist-info/WHEEL
qmpy-1.4.0.dist-info/top_level.txt
qmpy-1.4.0.dist-info/RECORD
