Metadata-Version: 2.1
Name: qmpy
Version: 1.4.0
Summary: Suite of computational materials science tools
Home-page: http://pypi.python.org/pypi/qmpy
Author: The OQMD Development Team
Author-email: oqmd.questions@gmail.com
License: LICENSE.txt
Platform: UNKNOWN
Classifier: Programming Language :: Python :: 3.7
Requires-Dist: Django (<2.3)
Requires-Dist: PuLP
Requires-Dist: numpy
Requires-Dist: scipy
Requires-Dist: mysqlclient
Requires-Dist: matplotlib
Requires-Dist: networkx
Requires-Dist: pytest
Requires-Dist: python-memcached
Requires-Dist: ase
Requires-Dist: django-extensions (>2.2.5)
Requires-Dist: lxml
Requires-Dist: spglib (>1.10)
Requires-Dist: PyCifRW (>=4.3)
Requires-Dist: pexpect
Requires-Dist: pyparsing
Requires-Dist: PyYAML
Requires-Dist: scikit-learn
Requires-Dist: bokeh
Requires-Dist: djangorestframework (>3.10.0)
Requires-Dist: djangorestframework-xml
Requires-Dist: djangorestframework-yaml
Requires-Dist: djangorestframework-queryfields
Requires-Dist: djangorestframework-filters
Requires-Dist: django-crispy-forms
Requires-Dist: lark-parser
Requires-Dist: requests
Requires-Dist: pygraphviz
Requires-Dist: Jinja2 (<3.0)
